{
    "description": "Security focused static analysis linter & fixer for GitHub Actions.",
    "version": "0.9.17",
    "homepage": "https://github.com/guitarrapc/seiton",
    "license": "MIT",
    "architecture": {
        "64bit": {
            "url": "https://github.com/guitarrapc/seiton/releases/download/v0.9.17/seiton-win-amd64.zip",
            "hash": "2c01765b5733a04dab31ecd8d86eba8bb5f9db457c79f3d516c8c293f957cd5d"
        },
        "arm64": {
            "url": "https://github.com/guitarrapc/seiton/releases/download/v0.9.17/seiton-win-arm64.zip",
            "hash": "2e017eeadda2242050b14dd96a63dc9b37447c5dc1f57f0da26807d7273789f5"
        }
    },
    "bin": "seiton.exe",
    "checkver": "github",
    "autoupdate": {
        "architecture": {
            "64bit": {
                "url": "https://github.com/guitarrapc/seiton/releases/download/v$version/seiton-win-amd64.zip"
            },
            "arm64": {
                "url": "https://github.com/guitarrapc/seiton/releases/download/v$version/seiton-win-arm64.zip"
            }
        }
    }
}
